{
  "todos": [
    {
      "id": "c5ecdd7f-9dee-4dd8-af37-8b89771fbce5",
      "body": "1",
      "status": true,
      "title": "1"
    },
    {
      "id": "81433b72-234c-4bbc-a3ad-5e53582f5790",
      "body": "2",
      "status": false,
      "title": "22"
    },
    {
      "id": "603079dd-4c1a-4e86-a2a2-4e2423f4014a",
      "body": "test1 ",
      "status": false,
      "title": "test "
    },
    {
      "id": "f6990110-1215-4929-b71e-6ff90ba5cfb1",
      "body": "dsadasd",
      "status": true,
      "title": "dasda13444"
    }
  ]
}